target_s3_delta/__init__.py
target_s3_delta/common.py
target_s3_delta/sinks.py
target_s3_delta/target.py
target_s3_delta/utils.py
target_s3_delta-0.0.25.dist-info/METADATA
target_s3_delta-0.0.25.dist-info/WHEEL
target_s3_delta-0.0.25.dist-info/entry_points.txt
target_s3_delta-0.0.25.dist-info/RECORD
