Metadata-Version: 2.1
Name: target-s3-delta
Version: 0.0.25
Summary: `target-s3-delta` is a Singer target for s3-delta, built with the Meltano Singer SDK.
License: Apache 2.0
Keywords: ELT,s3-delta
Author: resul yurttakalan
Requires-Python: >=3.8,<3.12
Classifier: License :: Other/Proprietary License
Classifier: Programming Language :: Python :: 3
Classifier: Programming Language :: Python :: 3.8
Classifier: Programming Language :: Python :: 3.9
Classifier: Programming Language :: Python :: 3.10
Classifier: Programming Language :: Python :: 3.11
Requires-Dist: deltalake (>=0.10.0,<0.11.0)
Requires-Dist: pandas (>=2.0.1,<3.0.0)
Requires-Dist: requests (>=2.28.2,<3.0.0)
Requires-Dist: singer-sdk (>=0.26.0,<0.27.0)
